setup.py
fsc_distributions/Binomialdistribution.py
fsc_distributions/Gaussiandistribution.py
fsc_distributions/Generaldistribution.py
fsc_distributions/__init__.py
fsc_distributions.egg-info/PKG-INFO
fsc_distributions.egg-info/SOURCES.txt
fsc_distributions.egg-info/dependency_links.txt
fsc_distributions.egg-info/not-zip-safe
fsc_distributions.egg-info/top_level.txt