Metadata-Version: 2.1
Name: fsc-distributions
Version: 1.4
Summary: Gaussian and binomial distribution classes
Author: FarahS
